bren/__init__.py
bren/keras_LICENCE_copy
bren/tensorflow_LICENCE_copy
bren/autodiff/__init__.py
bren/autodiff/nodes/Const.py
bren/autodiff/nodes/Graph.py
bren/autodiff/nodes/Node.py
bren/autodiff/nodes/Operator.py
bren/autodiff/nodes/Var.py
bren/autodiff/nodes/__init__.py
bren/autodiff/operations/__init__.py
bren/autodiff/operations/ops.py
bren/core/Array.py
bren/core/__init__.py
bren/core/core.py
bren/nn/__init__.py
bren/nn/utils.py
bren/nn/activations/Activation.py
bren/nn/activations/ELU.py
bren/nn/activations/Linear.py
bren/nn/activations/ReLU.py
bren/nn/activations/Tanh.py
bren/nn/activations/__init__.py
bren/nn/datasets/__init__.py
bren/nn/datasets/mnist.py
bren/nn/initialisers/GlorotNormal.py
bren/nn/initialisers/GlorotUniform.py
bren/nn/initialisers/HeNormal.py
bren/nn/initialisers/HeUniform.py
bren/nn/initialisers/Initialiser.py
bren/nn/initialisers/__init__.py
bren/nn/layers/Flatten.py
bren/nn/layers/FullyConnected.py
bren/nn/layers/Layer.py
bren/nn/layers/Softmax.py
bren/nn/layers/__init__.py
bren/nn/losses/CatrgoricalCrossEntropy.py
bren/nn/losses/Loss.py
bren/nn/losses/MeanSquaredError.py
bren/nn/losses/__init__.py
bren/nn/metrics/Accuracy.py
bren/nn/metrics/CategoricalCrossEntropy.py
bren/nn/metrics/MeanSquaredError.py
bren/nn/metrics/Metric.py
bren/nn/metrics/__init__.py
bren/nn/models/Model.py
bren/nn/models/Sequential.py
bren/nn/models/__init__.py
bren/nn/optimisers/AdaGrad.py
bren/nn/optimisers/Adam.py
bren/nn/optimisers/Optimiser.py
bren/nn/optimisers/RMSProp.py
bren/nn/optimisers/SGD.py
bren/nn/optimisers/__init__.py
bren/nn/preprocessing/__init__.py
bren/nn/preprocessing/utils.py
bren-0.1.8.dist-info/LICENSE
bren-0.1.8.dist-info/METADATA
bren-0.1.8.dist-info/WHEEL
bren-0.1.8.dist-info/top_level.txt
bren-0.1.8.dist-info/RECORD
