Metadata-Version: 2.1
Name: bren
Version: 0.1.8
Summary: A simple numpy based neural network library inspired by tensorflow/keras.
Author: Om Panchal
Author-email: om.panchal2022@gmail.com
Maintainer: Om Panchal
Maintainer-email: om.panchal2022@gmail.com
License: MIT
Classifier: Programming Language :: Python
Classifier: License :: OSI Approved :: MIT License
License-File: LICENSE
Requires-Dist: numpy
Requires-Dist: requests
